igtagger/__init__.py
igtagger/annotations.py
igtagger/atomic_sentences.py
igtagger/backend.py
igtagger/frontend.py
igtagger/ig_script.py
igtagger/sentence_type.py
igtagger/sentence_type_classifier.joblib
igtagger/annotator/__init__.py
igtagger/annotator/annotator.py
igtagger/annotator/ig_annotator.py
igtagger/annotator/lexical_tree.py
igtagger/annotator/stanford_annotator.py
igtagger/output/__init__.py
igtagger/output/tsv.py
igtagger/rulesexecutor/__init__.py
igtagger/rulesexecutor/ig_element.py
igtagger/rulesexecutor/rules.py
igtagger/rulesexecutor/rules_english_constitutive.py
igtagger/rulesexecutor/rules_english_regulative.py
igtagger/rulesexecutor/rules_executor.py
ig_tagger-1.3.5.dist-info/LICENSE
ig_tagger-1.3.5.dist-info/METADATA
ig_tagger-1.3.5.dist-info/WHEEL
ig_tagger-1.3.5.dist-info/entry_points.txt
ig_tagger-1.3.5.dist-info/top_level.txt
ig_tagger-1.3.5.dist-info/RECORD
